README.md
setup.cfg
setup.py
st_deeplink/__init__.py
streamlit_deeplink.egg-info/PKG-INFO
streamlit_deeplink.egg-info/SOURCES.txt
streamlit_deeplink.egg-info/dependency_links.txt
streamlit_deeplink.egg-info/requires.txt
streamlit_deeplink.egg-info/top_level.txt